{
  "slug": "australia-rockhampton",
  "title": "록햄프턴 가성비 호텔 7곳 비교 — 실제 리뷰·역세권 기준",
  "metaDescription": "AI가 실제 아고다 리뷰 데이터를 분석해 록햄프턴 가성비 호텔 7곳을 거리·평점·가격·가성비지수로 비교했습니다.",
  "lang": "ko-kr",
  "citySlug": "rockhampton-au",
  "cityName": "록햄프턴",
  "cityId": 13685,
  "refName": "각 호텔 최단 역",
  "refShort": "최단 역",
  "areaName": "록햄프턴",
  "heroImg": "https://pix8.agoda.net/hotelImages/626/626381/626381_14052608440019565282.jpg?ca=2&ce=1",
  "heroAlt": "록햄프턴",
  "heroTitleHtml": "록햄프턴 가성비 호텔 7곳<br>실제 리뷰·역세권 비교",
  "heroSub": "실제 아고다 리뷰 데이터를 분석해 거리·평점·가격·가성비를 한눈에",
  "verdictHtml": "가성비 1위는 <b>데이비드 모토 인</b>(평점 8.5·리뷰 371건·1박 약 11만원)로 가격 대비 만족도가 가장 높습니다. 역 접근성을 우선한다면 <b>Park Avenue 도보 4분</b>의 <b>Park Avenue Hotel Motel</b>를 추천합니다.",
  "outroImg": "https://pix8.agoda.net/hotelImages/626/626381/626381_14052608440019565282.jpg?ca=2&ce=1",
  "outroTitle": "🌙 록햄프턴, 어디에 묵어도 후회없이",
  "outroText": "위 7곳은 모두 록햄프턴 역세권의 검증된 가성비 숙소입니다. 날짜가 정해졌다면 아고다에서 록햄프턴 전체 숙소를 한 번에 비교해보세요.",
  "seasons": [],
  "hotels": [
    {
      "rank": 1,
      "name": "데이비드 모토 인 (David Motor Inn)",
      "hotelSlug": "",
      "agodaUrl": "https://www.agoda.com/david-motor-inn/hotel/rockhampton-au.html?cid=1925461",
      "walkMin": 16,
      "score": 8.5,
      "reviewCount": 371,
      "priceBand": 2,
      "priceText": "₩₩ · 약 11만원",
      "valueIndex": 7.1,
      "img": "//pix8.agoda.net/hotelImages/626/626381/626381_14052608440019565282.jpg?ca=2&ce=1",
      "distanceNote": "약 1241.98m · Park Avenue 인근",
      "metaTags": [
        "💰 약 11만원",
        "📝 리뷰 371건",
        "⭐ 3.5성급",
        "📶 무료 Wi-Fi"
      ],
      "reviewKeywordsHtml": "평점 <b>8.5</b> · 실제 투숙객 리뷰 371건 기반.",
      "reviews": [
        {
          "text": "이 3성급 숙소에 매우 놀랐습니다.",
          "score": "10",
          "country": "Australia",
          "date": "2024.08",
          "translated": true
        },
        {
          "text": "방은 깨끗하고 직원들은 매우 친절하고 협조적입니다.",
          "score": "9.6",
          "country": "Singapore",
          "date": "2025.10",
          "translated": true
        },
        {
          "text": "우리가 필요로 했던 것에 적합하고 예산 친화적이며 위치가 좋습니다.",
          "score": "8",
          "country": "Australia",
          "date": "2026.03",
          "translated": true
        },
        {
          "text": "가격대비 훌륭함 오래되었지만 매우 깨끗하고 잘 관리됨",
          "score": "9.6",
          "country": "Australia",
          "date": "2024.10",
          "translated": true
        },
        {
          "text": "매우 깨끗하고 모든 것이 단기 체류에 완벽했습니다.",
          "score": "9.6",
          "country": "Australia",
          "date": "2025.03",
          "translated": true
        }
      ],
      "ctaText": "🏨 최저가·예약창 가격 확인"
    },
    {
      "rank": 2,
      "name": "Criterion Hotel-Motel Rockhampton",
      "hotelSlug": "",
      "agodaUrl": "https://www.agoda.com/criterion-hotel-motel-rockhampton_3/hotel/all/rockhampton-au.html?cid=1925461",
      "walkMin": 13,
      "score": 8.2,
      "reviewCount": 125,
      "priceBand": 2,
      "priceText": "₩₩ · 약 9만원",
      "valueIndex": 6.8,
      "img": "//q-xx.bstatic.com/xdata/images/hotel/max500/467153816.jpg?k=8c19b0bf71576e2eb0da2beea6a9e92a1c891df877721f316134663e7cf04c3d&o=",
      "distanceNote": "약 1040.03m · Glemore Junction 인근",
      "metaTags": [
        "💰 약 9만원",
        "📝 리뷰 125건",
        "⭐ 3성급",
        "📶 무료 Wi-Fi"
      ],
      "reviewKeywordsHtml": "평점 <b>8.2</b> · 실제 투숙객 리뷰 125건 기반.",
      "reviews": [
        {
          "text": "중심부의 아름다운 위치에 있는 훌륭한 저예산 숙박",
          "score": "8.8",
          "country": "Australia",
          "date": "2024.08",
          "translated": true
        },
        {
          "text": "모든 필요 사항을 충족할 수 있는 도보 거리에 있는 CBD의 심장부를 뛰게 합니다.",
          "score": "8.4",
          "country": "Australia",
          "date": "2024.06",
          "translated": true
        },
        {
          "text": "그들은 제가 머무는 동안 저를 돕기 위해 최선을 다했습니다.",
          "score": "9.6",
          "country": "Australia",
          "date": "2025.02",
          "translated": true
        },
        {
          "text": "직원들이 매우 친절하고 숙소도 깨끗합니다.",
          "score": "9.6",
          "country": "Australia",
          "date": "2025.07",
          "translated": true
        },
        {
          "text": "직원들은 매우 친절하고 도움이 되었습니다.",
          "score": "9.6",
          "country": "Australia",
          "date": "2025.02",
          "translated": true
        }
      ],
      "ctaText": "🏨 최저가·예약창 가격 확인"
    },
    {
      "rank": 3,
      "name": "Park Avenue Hotel Motel",
      "hotelSlug": "",
      "agodaUrl": "https://www.agoda.com/park-avenue-hotel-motel/hotel/all/rockhampton-au.html?cid=1925461",
      "walkMin": 4,
      "score": 8.1,
      "reviewCount": 798,
      "priceBand": 2,
      "priceText": "₩₩ · 약 11만원",
      "valueIndex": 6.8,
      "img": "//q-xx.bstatic.com/xdata/images/hotel/max500/276617487.jpg?k=a53e55ed21dba94eda9d8d35cb674d46be7081ed7d535afb85f6eaba33e5210f&o=",
      "distanceNote": "약 288.5m · Park Avenue 인근",
      "metaTags": [
        "💰 약 11만원",
        "📝 리뷰 798건",
        "⭐ 3성급",
        "📶 무료 Wi-Fi"
      ],
      "reviewKeywordsHtml": "평점 <b>8.1</b> · 실제 투숙객 리뷰 798건 기반.",
      "reviews": [
        {
          "text": "훌륭한 펍 레스토랑이 있는 호텔/모텔에 숙박하세요.",
          "score": "9.6",
          "country": "Australia",
          "date": "2026.02",
          "translated": true
        },
        {
          "text": "단지 침대와 훌륭한 식사가 필요한 경우 훌륭한 가치를 제공합니다.",
          "score": "8",
          "country": "Australia",
          "date": "2023.08",
          "translated": true
        },
        {
          "text": "1인 여행자에게 훌륭한 숙소입니다.",
          "score": "9.6",
          "country": "Australia",
          "date": "2026.02",
          "translated": true
        },
        {
          "text": "훌륭한 방, 훌륭한 서비스, 훌륭한 음식과 시원한 맥주.",
          "score": "10",
          "country": "Australia",
          "date": "2026.03",
          "translated": true
        },
        {
          "text": "방은 에어컨과 평면 스크린으로 깨끗하고 깔끔했습니다.",
          "score": "10",
          "country": "Australia",
          "date": "2022.06",
          "translated": true
        }
      ],
      "ctaText": "🏨 최저가·예약창 가격 확인"
    },
    {
      "rank": 4,
      "name": "Riverside Tourist Park",
      "hotelSlug": "",
      "agodaUrl": "https://www.agoda.com/riverside-tourist-park/hotel/all/rockhampton-au.html?cid=1925461",
      "walkMin": 8,
      "score": 8.1,
      "reviewCount": 798,
      "priceBand": 2,
      "priceText": "₩₩ · 약 12만원",
      "valueIndex": 6.8,
      "img": "//pix8.agoda.net/hotelImages/886034/0/9cf515ec0ffe3e1499bfa6be6437d673.jpeg?ce=0",
      "distanceNote": "약 672.88m · Glemore Junction 인근",
      "metaTags": [
        "💰 약 12만원",
        "📝 리뷰 798건",
        "⭐ 4성급",
        "📶 무료 Wi-Fi"
      ],
      "reviewKeywordsHtml": "평점 <b>8.1</b> · 실제 투숙객 리뷰 798건 기반.",
      "reviews": [
        {
          "text": "편안한 분위기, 친절한 리셉션, 깨끗한 환경.",
          "score": "9.2",
          "country": "Australia",
          "date": "2026.03",
          "translated": true
        },
        {
          "text": "매우 편안하고 좋은 가치를 지닌 캐빈",
          "score": "10",
          "country": "Australia",
          "date": "2025.10",
          "translated": true
        },
        {
          "text": "편안하고 깨끗하며 가격 대비 가치가 높습니다.",
          "score": "10",
          "country": "Australia",
          "date": "2025.10",
          "translated": true
        },
        {
          "text": "그것은 깨끗했고 우리가 밤에 필요한 것에 딱 맞았습니다.",
          "score": "9.6",
          "country": "Australia",
          "date": "2025.01",
          "translated": true
        },
        {
          "text": "사랑스러운 작은 오두막, 깨끗한 공원과 시설,",
          "score": "9.6",
          "country": "Australia",
          "date": "2024.02",
          "translated": true
        }
      ],
      "ctaText": "🏨 최저가·예약창 가격 확인"
    },
    {
      "rank": 5,
      "name": "Casa Nostra Motel",
      "hotelSlug": "",
      "agodaUrl": "https://www.agoda.com/casa-nostra-motel/hotel/rockhampton-au.html?cid=1925461",
      "walkMin": 98,
      "score": 9.1,
      "reviewCount": 1301,
      "priceBand": 3,
      "priceText": "₩₩ · 약 16만원",
      "valueIndex": 6.7,
      "img": "//q-xx.bstatic.com/xdata/images/hotel/max500/643791460.jpg?k=dab575d0512785f6b21a80efd9e68668c672f2052db4237c8f0604e93d14e368&o=",
      "distanceNote": "약 7811.02m · Park Avenue 인근",
      "metaTags": [
        "💰 약 16만원",
        "📝 리뷰 1,301건",
        "⭐ 4성급",
        "📶 무료 Wi-Fi"
      ],
      "reviewKeywordsHtml": "평점 <b>9.1</b> · 실제 투숙객 리뷰 1,301건 기반.",
      "reviews": [
        {
          "text": "매우 편안한 매트리스를 갖춘 거대한 킹 사이즈 침대.",
          "score": "9.6",
          "country": "Australia",
          "date": "2023.05",
          "translated": true
        },
        {
          "text": "와, 방은 거대하고, 새롭고, 깨끗하고, 정말 잘 꾸며져 있습니다.",
          "score": "9.6",
          "country": "Australia",
          "date": "2023.05",
          "translated": true
        },
        {
          "text": "솔직히 제가 머물렀던 최고의 장소 중 하나입니다.",
          "score": "10",
          "country": "Australia",
          "date": "2022.05",
          "translated": true
        },
        {
          "text": "4인용 테이블과 평면 스크린을 향한 소파.",
          "score": "9.6",
          "country": "Australia",
          "date": "2023.05",
          "translated": true
        },
        {
          "text": "나는 확실히 추천합니다. 직원은 사랑스럽고 소란스럽지 않았습니다.",
          "score": "10",
          "country": "Australia",
          "date": "2026.03",
          "translated": true
        }
      ],
      "ctaText": "🏨 최저가·예약창 가격 확인"
    },
    {
      "rank": 6,
      "name": "Quality Resort Parkhurst",
      "hotelSlug": "",
      "agodaUrl": "https://www.agoda.com/korte-s-resort/hotel/rockhampton-au.html?cid=1925461",
      "walkMin": 94,
      "score": 9,
      "reviewCount": 1630,
      "priceBand": 3,
      "priceText": "₩₩ · 약 17만원",
      "valueIndex": 6.6,
      "img": "//q-xx.bstatic.com/xdata/images/hotel/max500/890033009.jpg?k=b311a455da084489fccf8dbb0f3877a12d43a8262a3dbf1a6d317e5013c6134f&o=",
      "distanceNote": "약 7558.42m · Park Avenue 인근",
      "metaTags": [
        "💰 약 17만원",
        "📝 리뷰 1,630건",
        "⭐ 3성급",
        "📶 무료 Wi-Fi"
      ],
      "reviewKeywordsHtml": "평점 <b>9</b> · 실제 투숙객 리뷰 1,630건 기반.",
      "reviews": [
        {
          "text": "깨끗했고 숙박에 필요한 모든 것이 갖춰져 있었습니다.",
          "score": "8.8",
          "country": "Australia",
          "date": "2025.02",
          "translated": true
        },
        {
          "text": "우리는 여기에 여러 번 머물렀고 결코 실망하지 않았습니다.",
          "score": "10",
          "country": "Australia",
          "date": "2025.10",
          "translated": true
        },
        {
          "text": "기회가 주어진다면 꼭 다시 올 것이다",
          "score": "10",
          "country": "Singapore",
          "date": "2024.01",
          "translated": true
        },
        {
          "text": "우리가 Rocky에 있을 때마다 꼭 가는 호텔이 되었습니다.",
          "score": "10",
          "country": "Australia",
          "date": "2025.10",
          "translated": true
        },
        {
          "text": "매우 깨끗한 인테리어를 갖춘 매우 쾌적한 직원.",
          "score": "10",
          "country": "Singapore",
          "date": "2024.01",
          "translated": true
        }
      ],
      "ctaText": "🏨 최저가·예약창 가격 확인"
    },
    {
      "rank": 7,
      "name": "시티워크 모터 인 (Citywalk Motor Inn)",
      "hotelSlug": "",
      "agodaUrl": "https://www.agoda.com/citywalk-motor-inn_2/hotel/all/rockhampton-au.html?cid=1925461",
      "walkMin": 9,
      "score": 9,
      "reviewCount": 658,
      "priceBand": 3,
      "priceText": "₩₩ · 약 17만원",
      "valueIndex": 6.6,
      "img": "//q-xx.bstatic.com/xdata/images/hotel/max500/486247794.jpg?k=225c18402f573f1d604b3c8685d91360fbefb7c746938ffa255fc8561539438f&o=",
      "distanceNote": "약 733.25m · Rockhampton Railway Station 인근",
      "metaTags": [
        "💰 약 17만원",
        "📝 리뷰 658건",
        "⭐ 3.5성급",
        "📶 무료 Wi-Fi"
      ],
      "reviewKeywordsHtml": "평점 <b>9</b> · 실제 투숙객 리뷰 658건 기반.",
      "reviews": [
        {
          "text": "내가 전에 살았던 가장 깨끗한 호텔.",
          "score": "10",
          "country": "澳洲",
          "date": "2024.05",
          "translated": true
        },
        {
          "text": "흠집이 없다는 리뷰는 합법적이었습니다.",
          "score": "10",
          "country": "Singapore",
          "date": "2025.06",
          "translated": true
        },
        {
          "text": "매우 친절하고 유익한 리셉션 직원.",
          "score": "9.6",
          "country": "Australia",
          "date": "2024.05",
          "translated": true
        },
        {
          "text": "기본 숙박 시설이 매우 잘 이루어졌습니다.",
          "score": "9.6",
          "country": "Australia",
          "date": "2022.08",
          "translated": true
        },
        {
          "text": "깨끗하고 편안하며 도로 소음이 약간 있습니다.",
          "score": "8",
          "country": "Philippines",
          "date": "2024.10",
          "translated": true
        }
      ],
      "ctaText": "🏨 최저가·예약창 가격 확인"
    }
  ],
  "_meta": {
    "fetchedAt": "2026-07-13T20:21:20.250Z",
    "source": "agoda citySearch",
    "count": 7
  }
}